paclare/.ruff_cache/.gitignore
paclare/.ruff_cache/0.12.9/17461901716904035128
paclare/.ruff_cache/0.12.9/5228129816550906064
paclare/.ruff_cache/CACHEDIR.TAG
paclare/__init__.py
paclare/commands.py
paclare/config.py
paclare/logs.py
paclare/main.py
paclare/options.py
paclare/packagemanagers.py
paclare/shell.py
paclare-0.1.1.dist-info/WHEEL
paclare-0.1.1.dist-info/entry_points.txt
paclare-0.1.1.dist-info/METADATA
paclare-0.1.1.dist-info/RECORD
