Metadata-Version: 2.4
Name: paclare
Version: 0.1.1
Summary: Maintain your installed packages from a source file
Author: Charles Gonnaud
License-Expression: GPL-3.0-or-later
Requires-Python: >=3.12
Project-URL: Homepage, https://github.com/Horrih/paclare
Project-URL: Issues, https://github.com/Horrih/paclare/issues
